EnsemblePursuit/EnsemblePursuit.py
EnsemblePursuit/__init__.py
EnsemblePursuit/utils.py
Notebooks/__init__.py
EnsemblePursuit-0.0.3.dist-info/LICENSE
EnsemblePursuit-0.0.3.dist-info/METADATA
EnsemblePursuit-0.0.3.dist-info/WHEEL
EnsemblePursuit-0.0.3.dist-info/top_level.txt
EnsemblePursuit-0.0.3.dist-info/RECORD
