Metadata-Version: 2.1
Name: EnsemblePursuit
Version: 0.0.3
Summary: A sparse matrix factorization algorithm for extracting co-activating neurons from large-scale recordings
Home-page: https://github.com/MouseLand/EnsemblePursuit
Author: Marius Pachitariu, Carsen Stringer, Maria Kesa
Author-email: maria.kesa@gmail.com
License: UNKNOWN
Platform: UNKNOWN
Classifier: Programming Language :: Python :: 3
Classifier: License :: OSI Approved :: GNU General Public License v3 (GPLv3)
Classifier: Operating System :: OS Independent
Requires-Python: >=3.6
Requires-Dist: numpy (>=1.13.0)
Requires-Dist: scipy
Requires-Dist: scikit-learn
Requires-Dist: torch
